tests/__init__.py
tests/test_collection.py
zhaogang_collec/__init__.py
zhaogang_collec/main.py
zhaogang_collec-0.0.3.dist-info/METADATA
zhaogang_collec-0.0.3.dist-info/WHEEL
zhaogang_collec-0.0.3.dist-info/entry_points.txt
zhaogang_collec-0.0.3.dist-info/top_level.txt
zhaogang_collec-0.0.3.dist-info/RECORD
